spaps_server_quickstart/__init__.py
spaps_server_quickstart/app_factory.py
spaps_server_quickstart/auth_channels.py
spaps_server_quickstart/logging.py
spaps_server_quickstart/middleware.py
spaps_server_quickstart/secure_messaging.py
spaps_server_quickstart/settings.py
spaps_server_quickstart/alembic/__init__.py
spaps_server_quickstart/alembic/naming.py
spaps_server_quickstart/api/__init__.py
spaps_server_quickstart/api/health.py
spaps_server_quickstart/api/router.py
spaps_server_quickstart/auth/__init__.py
spaps_server_quickstart/auth/cookies.py
spaps_server_quickstart/auth/dependencies.py
spaps_server_quickstart/db/__init__.py
spaps_server_quickstart/db/alembic_status.py
spaps_server_quickstart/db/migration_runner.py
spaps_server_quickstart/db/session.py
spaps_server_quickstart/rbac/__init__.py
spaps_server_quickstart/schemas/__init__.py
spaps_server_quickstart/schemas/health.py
spaps_server_quickstart/tasks/__init__.py
spaps_server_quickstart/tasks/celery_factory.py
spaps_server_quickstart/tasks/health.py
spaps_server_quickstart/tasks/notifications.py
spaps_server_quickstart/templates/__init__.py
spaps_server_quickstart/templates/domains/__init__.py
spaps_server_quickstart/templates/domains/admin/router.py
spaps_server_quickstart/templates/domains/users/router.py
spaps_server_quickstart/templates/operations/.env.production.example
spaps_server_quickstart/templates/operations/Makefile
spaps_server_quickstart/templates/operations/docker-compose.prod.yml
spaps_server_quickstart/templates/operations/.githooks/pre-push
spaps_server_quickstart/templates/operations/deploy/deploy.sh
spaps_server_quickstart/templates/operations/scripts/backup-db.sh
spaps_server_quickstart/templates/operations/scripts/new-migration.sh
spaps_server_quickstart/templates/operations/scripts/prepush.sh
spaps_server_quickstart/templates/operations/scripts/restore-db.sh
spaps_server_quickstart-0.2.0.dist-info/METADATA
spaps_server_quickstart-0.2.0.dist-info/WHEEL
spaps_server_quickstart-0.2.0.dist-info/RECORD
