Metadata-Version: 2.4
Name: spaps-server-quickstart
Version: 0.2.0
Summary: Shared FastAPI/Celery scaffolding for Sweet Potato service backends.
Project-URL: Repository, https://github.com/sweet-potato/spaps
Author-email: buildooor <buildooor@gmail.com>
License: Proprietary
Keywords: celery,fastapi,quickstart,spaps,sweet-potato
Requires-Python: >=3.12
Requires-Dist: alembic<2.0,>=1.13.1
Requires-Dist: asyncpg<0.31,>=0.30.0
Requires-Dist: celery<6.0,>=5.5.3
Requires-Dist: email-validator<3.0,>=2.1.0
Requires-Dist: fastapi<0.119,>=0.118.0
Requires-Dist: greenlet<4.0,>=3.0.3
Requires-Dist: httpx<0.29,>=0.28.1
Requires-Dist: pgvector<0.5,>=0.4.1
Requires-Dist: psycopg[binary]<3.3,>=3.2.10
Requires-Dist: pydantic-settings<3.0,>=2.3.0
Requires-Dist: pydantic<3.0,>=2.8.0
Requires-Dist: python-dotenv<2.0,>=1.0.1
Requires-Dist: redis<7.0,>=6.4.0
Requires-Dist: spaps>=0.1.2
Requires-Dist: sqlalchemy<3.0,>=2.0.30
Requires-Dist: structlog<26.0,>=25.4.0
Requires-Dist: uvicorn[standard]<0.38,>=0.37.0
Provides-Extra: dev
Requires-Dist: anyio<5.0,>=4.4.0; extra == 'dev'
Requires-Dist: coverage<8.0,>=7.4.0; extra == 'dev'
Requires-Dist: mypy<1.12,>=1.10.0; extra == 'dev'
Requires-Dist: pytest-asyncio<0.24,>=0.23.0; extra == 'dev'
Requires-Dist: pytest-cov<6.0,>=5.0.0; extra == 'dev'
Requires-Dist: pytest<9.0,>=8.2.0; extra == 'dev'
Requires-Dist: ruff<0.5,>=0.4.1; extra == 'dev'
Provides-Extra: release
Requires-Dist: build<2.0,>=1.2.1; extra == 'release'
Requires-Dist: twine<6.0,>=5.0.0; extra == 'release'
